fastapi_gql/__init__.py
fastapi_gql/app.py
fastapi_gql/controllers/index.py
fastapi_gql/controllers/user.py
fastapi_gql/graphql/types.py
fastapi_gql/infra/database.py
fastapi_gql/models/index.py
fastapi_gql/models/user.py
fastapi_gql-0.1.0.dist-info/LICENSE
fastapi_gql-0.1.0.dist-info/METADATA
fastapi_gql-0.1.0.dist-info/WHEEL
fastapi_gql-0.1.0.dist-info/entry_points.txt
fastapi_gql-0.1.0.dist-info/RECORD
